{
  "$schema": "https://mintlify.com/docs.json",
  "name": "Wiki Education Dashboard",
  "theme": "almond",
  "colors": {
    "primary": "#949494",
    "light": "#2b2b2b",
    "dark": "#bebebe"
  },
  "favicon": "https://media.brand.dev/af394c04-7528-405c-997d-6c8aee8487ec.png",
  "navbar": {
    "primary": {
      "type": "github",
      "href": "https://github.com/WikiEducationFoundation/WikiEduDashboard"
    }
  },
  "footer": {
    "socials": {
      "github": "https://github.com/WikiEducationFoundation/WikiEduDashboard"
    }
  },
  "navigation": {
    "tabs": [
      {
        "tab": "Documentation",
        "groups": [
          {
            "group": "Get Started",
            "pages": [
              "introduction",
              "setup",
              "docker"
            ]
          },
          {
            "group": "Core Features",
            "pages": [
              "courses-and-campaigns",
              "user-roles",
              "training-modules",
              "analytics-pipeline"
            ]
          },
          {
            "group": "Configuration",
            "pages": [
              "configuration",
              "oauth-setup",
              "internationalization",
              "multiwiki"
            ]
          },
          {
            "group": "Contributing",
            "pages": [
              "contributing",
              "testing",
              "frontend-architecture",
              "deployment"
            ]
          }
        ]
      },
      {
        "tab": "Operations",
        "groups": [
          {
            "group": "Infrastructure",
            "pages": [
              "operations/admin-guide",
              "operations/infrastructure-overview",
              "operations/monitoring"
            ]
          },
          {
            "group": "Troubleshooting",
            "pages": [
              "operations/troubleshooting",
              "operations/production-troubleshooting"
            ]
          }
        ]
      }
    ]
  }
}
